raytrace_jax/__init__.py
raytrace_jax-0.0.2.dist-info/METADATA
raytrace_jax-0.0.2.dist-info/WHEEL
raytrace_jax-0.0.2.dist-info/licenses/LICENSE
raytrace_jax-0.0.2.dist-info/RECORD
