Metadata-Version: 2.4
Name: raytrace_jax
Version: 0.0.2
Summary: The Ray Tracing Sampler, JAX interface.
Project-URL: Homepage, https://bitbucket.org/pbehroozi/ray-tracing-sampler/src/main/
Author-email: Peter Behroozi <behroozi@arizona.edu>
License-Expression: Apache-2.0
License-File: LICENSE
Keywords: machine learning,mcmc,pytorch,sampling,statistics
Classifier: Operating System :: OS Independent
Classifier: Programming Language :: Python :: 3
Requires-Python: >=3.9
Requires-Dist: jax>=0.4.30
Requires-Dist: numpy>=1.26.0
